.travis.yml
AUTHORS
ChangeLog
Notes.md
README.rst
requirements.txt
setup.cfg
setup.py
jenkins_job_builder_xvnc.egg-info/PKG-INFO
jenkins_job_builder_xvnc.egg-info/SOURCES.txt
jenkins_job_builder_xvnc.egg-info/dependency_links.txt
jenkins_job_builder_xvnc.egg-info/entry_points.txt
jenkins_job_builder_xvnc.egg-info/not-zip-safe
jenkins_job_builder_xvnc.egg-info/requires.txt
jenkins_job_builder_xvnc.egg-info/top_level.txt
sample/jenkins.ini
sample/sample-job.yml
tools/release.bash
xvnc_build_wrapper/__init__.py