Metadata-Version: 1.0
Name: jenkins-job-builder-xvnc
Version: 0.1
Summary: Enable xvnc for job execution.
Home-page: https://github.com/signed/jenkins-job-builder-xvnc
Author: Thomas Heilbronner
Author-email: thomas.heilbronner@gmail.com
License: Apache License, Version 2.0
Platform: UNKNOWN
